mapminer/__init__.py
mapminer/version.py
mapminer/miners/__init__.py
mapminer/miners/cdl_miner.py
mapminer/miners/dem_miner.py
mapminer/miners/esri_basemap_miner.py
mapminer/miners/esri_lulc_miner.py
mapminer/miners/foursquare_miner.py
mapminer/miners/google_basemap_miner.py
mapminer/miners/google_building_miner.py
mapminer/miners/google_embedding_miner.py
mapminer/miners/google_traffic_miner.py
mapminer/miners/landsat_miner.py
mapminer/miners/miner.py
mapminer/miners/modis_miner.py
mapminer/miners/ms_building_miner.py
mapminer/miners/naip_miner.py
mapminer/miners/osm_miner.py
mapminer/miners/sentinel1_miner.py
mapminer/miners/sentinel2_miner.py
mapminer/miners/keys/__init__.py
mapminer/miners/keys/google_service_account.json
mapminer/miners/keys/secret_key.key
mapminer/models/__init__.py
mapminer/models/convlstm.py
mapminer/models/dinochm.py
mapminer/models/dinov3.py
mapminer/models/nafnet.py
mapminer/models/sam3.py
mapminer-0.1.92.dist-info/licenses/LICENSE
mapminer-0.1.92.dist-info/METADATA
mapminer-0.1.92.dist-info/WHEEL
mapminer-0.1.92.dist-info/top_level.txt
mapminer-0.1.92.dist-info/RECORD
