Metadata-Version: 2.4
Name: mapminer
Version: 0.1.92
Summary: An advanced geospatial data extraction and processing toolkit for Earth observation datasets.
Home-page: https://github.com/gajeshladhar/mapminer
Author: Gajesh Ladhar
Author-email: gajeshladhar@gmail.com
License: MIT
Project-URL: Documentation, https://github.com/gajeshladhar/mapminer#readme
Project-URL: Source, https://github.com/gajeshladhar/mapminer
Project-URL: Tracker, https://github.com/gajeshladhar/mapminer/issues
Keywords: geospatial,GIS,Earth observation,satellite imagery,data processing,remote sensing,machine learning,map tiles,metadata extraction,planetary datasets,xarray,spatial analysis
Classifier: Development Status :: 3 - Alpha
Classifier: Intended Audience :: Developers
Classifier: Intended Audience :: Science/Research
Classifier: License :: OSI Approved :: MIT License
Classifier: Programming Language :: Python :: 3
Classifier: Programming Language :: Python :: 3.9
Classifier: Programming Language :: Python :: 3.10
Classifier: Programming Language :: Python :: 3.11
Classifier: Programming Language :: Python :: 3.12
Classifier: Topic :: Software Development :: Libraries :: Python Modules
Classifier: Topic :: Scientific/Engineering :: GIS
Classifier: Topic :: Scientific/Engineering :: Image Recognition
Classifier: Topic :: Scientific/Engineering :: Artificial Intelligence
Requires-Python: >=3.9
License-File: LICENSE
Requires-Dist: requests>=2.32.3
Requires-Dist: dask==2025.1.0
Requires-Dist: numpy>=1.24.0
Requires-Dist: pandas>=2.2.2
Requires-Dist: Pillow>=11.0.0
Requires-Dist: rasterio>=1.3.9
Requires-Dist: Requests>=2.32.3
Requires-Dist: Shapely>=2.0.6
Requires-Dist: xarray>=2024.2.0
Requires-Dist: hvplot
Requires-Dist: cryptography>=41.0.3
Requires-Dist: planetary_computer>=1.0.0
Requires-Dist: rioxarray>=0.15.0
Requires-Dist: xee==0.0.9
Requires-Dist: ipython
Requires-Dist: geopandas>=0.14.4
Requires-Dist: geoviews>=1.13.0
Requires-Dist: fsspec>=2024.3.1
Requires-Dist: duckdb>=1.1.3
Requires-Dist: zarr>=2.17.0
Requires-Dist: netCDF4
Requires-Dist: s3fs
Requires-Dist: mercantile==1.2.1
Requires-Dist: odc-stac==0.3.11
Requires-Dist: pystac_client==0.7.2
Requires-Dist: pystac==1.9.0
Requires-Dist: torch
Requires-Dist: torchmetrics
Requires-Dist: torchvision
Requires-Dist: joblib
Requires-Dist: huggingface_hub
Requires-Dist: transformers
Provides-Extra: all
Requires-Dist: requests>=2.32.3; extra == "all"
Requires-Dist: dask==2025.1.0; extra == "all"
Requires-Dist: numpy>=1.24.0; extra == "all"
Requires-Dist: pandas>=2.2.2; extra == "all"
Requires-Dist: Pillow>=11.0.0; extra == "all"
Requires-Dist: rasterio>=1.3.9; extra == "all"
Requires-Dist: Requests>=2.32.3; extra == "all"
Requires-Dist: Shapely>=2.0.6; extra == "all"
Requires-Dist: xarray>=2024.2.0; extra == "all"
Requires-Dist: hvplot; extra == "all"
Requires-Dist: cryptography>=41.0.3; extra == "all"
Requires-Dist: planetary_computer>=1.0.0; extra == "all"
Requires-Dist: rioxarray>=0.15.0; extra == "all"
Requires-Dist: xee==0.0.9; extra == "all"
Requires-Dist: ipython; extra == "all"
Requires-Dist: geopandas>=0.14.4; extra == "all"
Requires-Dist: geoviews>=1.13.0; extra == "all"
Requires-Dist: fsspec>=2024.3.1; extra == "all"
Requires-Dist: duckdb>=1.1.3; extra == "all"
Requires-Dist: zarr>=2.17.0; extra == "all"
Requires-Dist: netCDF4; extra == "all"
Requires-Dist: s3fs; extra == "all"
Requires-Dist: mercantile==1.2.1; extra == "all"
Requires-Dist: odc-stac==0.3.11; extra == "all"
Requires-Dist: pystac_client==0.7.2; extra == "all"
Requires-Dist: pystac==1.9.0; extra == "all"
Requires-Dist: torch; extra == "all"
Requires-Dist: torchmetrics; extra == "all"
Requires-Dist: torchvision; extra == "all"
Requires-Dist: joblib; extra == "all"
Requires-Dist: huggingface_hub; extra == "all"
Requires-Dist: transformers; extra == "all"
Requires-Dist: easyocr==1.7.1; extra == "all"
Requires-Dist: selenium>=4.23.1; extra == "all"
Requires-Dist: undetected_chromedriver==3.5.5; extra == "all"
Requires-Dist: paddlepaddle>=2.6.1; extra == "all"
Requires-Dist: paddleocr==2.8.1; extra == "all"
Requires-Dist: webdriver-manager>=4.0.2; extra == "all"
Dynamic: author
Dynamic: author-email
Dynamic: classifier
Dynamic: description
Dynamic: description-content-type
Dynamic: home-page
Dynamic: keywords
Dynamic: license
Dynamic: license-file
Dynamic: project-url
Dynamic: provides-extra
Dynamic: requires-dist
Dynamic: requires-python
Dynamic: summary
